mysa/__init__.py
mysa/core.py
mysa/dml.py
mysa/manager.py
mysa/models/__init__.py
mysa/models/base.py
mysa/models/mixins.py
mysa/models/schemas.py
mysa/models/utils.py
mysa-0.0.1.dist-info/METADATA
mysa-0.0.1.dist-info/WHEEL
mysa-0.0.1.dist-info/RECORD
