Metadata-Version: 2.1
Name: mysa
Version: 0.0.1
Summary: 
Author: Nafnix
Author-email: nafnix@proton.me
Requires-Python: >=3.11,<4.0
Classifier: Programming Language :: Python :: 3
Classifier: Programming Language :: Python :: 3.11
Requires-Dist: asyncpg (>=0.27.0,<0.28.0)
Requires-Dist: orjson (>=3.8.12,<4.0.0)
Requires-Dist: pydantic (>=1.10,<2.0)
Requires-Dist: sqlalchemy (>=2,<3)
